README.md
setup.py
metrodraw/__init__.py
metrodraw/interline.py
metrodraw/render.py
metrodraw/schemes.py
metrodraw/version.py
metrodraw.egg-info/PKG-INFO
metrodraw.egg-info/SOURCES.txt
metrodraw.egg-info/dependency_links.txt
metrodraw.egg-info/requires.txt
metrodraw.egg-info/top_level.txt
metrodraw/examples/__init__.py
metrodraw/model/__init__.py
metrodraw/model/coord.py
metrodraw/model/label.py
metrodraw/model/line.py
metrodraw/model/railmap.py
metrodraw/model/station.py
metrodraw/utils/__init__.py
metrodraw/utils/data_linewidth_plot.py