Metadata-Version: 2.1
Name: metrodraw
Version: 0.0.9
Summary: Allows you to create metro maps.
Home-page: https://github.com/kavigupta/metrodraw
Author: Kavi Gupta
Author-email: metrodraw@kavigupta.org
License: UNKNOWN
Platform: UNKNOWN
Classifier: Programming Language :: Python :: 3.8
Classifier: Programming Language :: Python :: 3.9
Classifier: Programming Language :: Python :: 3.10
Classifier: Programming Language :: Python :: 3.11
Classifier: Operating System :: OS Independent
Requires-Python: >=3.8
